pdmparse/__init__.py
pdmparse/api.py
pdmparse/parsers.py
pdmparse/table.py
pdmparse-1.0.3.dist-info/METADATA
pdmparse-1.0.3.dist-info/WHEEL
pdmparse-1.0.3.dist-info/top_level.txt
pdmparse-1.0.3.dist-info/RECORD
