Metadata-Version: 2.1
Name: pdmparse
Version: 1.0.3
Summary: 解析PowerDesigner的数据库设计pdm文件，用于模板代码生成
Home-page: https://github.com/9kl/pdmparse
Author: fhp
Author-email: chinafengheping@outlook.com
Classifier: Programming Language :: Python :: 3
Classifier: License :: OSI Approved :: MIT License
Classifier: Operating System :: OS Independent
Requires-Python: >=3.8
Requires-Dist: Jinja2 ==3.1.6
